escobar/__init__.py
escobar/_version.py
escobar/auth_handlers.py
escobar/handlers.py
escobar/labextension/package.json
escobar/labextension/schemas/escobar/package.json.orig
escobar/labextension/schemas/escobar/plugin.json
escobar/labextension/static/304.c0ec5455191313b692bf.js
escobar/labextension/static/346.45ab6773a5685968f1c0.js
escobar/labextension/static/379.60fc74dd168c21adbe22.js
escobar/labextension/static/57.53be9fe25dde4faffe42.js
escobar/labextension/static/64.f696cf3277e28ecac4fc.js
escobar/labextension/static/648.47047330549e0acbeda3.js
escobar/labextension/static/666.f584ba4ddd8aeacd48bd.js
escobar/labextension/static/874.700f6efe1f851b6e65af.js
escobar/labextension/static/986.79122e9bb2c773402881.js
escobar/labextension/static/remoteEntry.1beeb65023b8fe956db2.js
escobar/labextension/static/style.js
escobar/labextension/static/third-party-licenses.json
escobar/static/oauth-callback.html
escobar-0.1.147.data/data/share/jupyter/labextensions/escobar/package.json
escobar-0.1.147.data/data/share/jupyter/labextensions/escobar/schemas/escobar/package.json.orig
escobar-0.1.147.data/data/share/jupyter/labextensions/escobar/schemas/escobar/plugin.json
escobar-0.1.147.data/data/share/jupyter/labextensions/escobar/static/304.c0ec5455191313b692bf.js
escobar-0.1.147.data/data/share/jupyter/labextensions/escobar/static/346.45ab6773a5685968f1c0.js
escobar-0.1.147.data/data/share/jupyter/labextensions/escobar/static/379.60fc74dd168c21adbe22.js
escobar-0.1.147.data/data/share/jupyter/labextensions/escobar/static/57.53be9fe25dde4faffe42.js
escobar-0.1.147.data/data/share/jupyter/labextensions/escobar/static/64.f696cf3277e28ecac4fc.js
escobar-0.1.147.data/data/share/jupyter/labextensions/escobar/static/648.47047330549e0acbeda3.js
escobar-0.1.147.data/data/share/jupyter/labextensions/escobar/static/666.f584ba4ddd8aeacd48bd.js
escobar-0.1.147.data/data/share/jupyter/labextensions/escobar/static/874.700f6efe1f851b6e65af.js
escobar-0.1.147.dist-info/METADATA
escobar-0.1.147.dist-info/WHEEL
escobar-0.1.147.dist-info/entry_points.txt
escobar-0.1.147.dist-info/licenses/LICENSE
escobar-0.1.147.dist-info/RECORD
