Metadata-Version: 2.4
Name: escobar
Version: 0.1.147
Dynamic: Keywords
Summary: AI CHAT EXTENSION
Project-URL: Homepage, https://github.com/github_username/escobar
Project-URL: Bug Tracker, https://github.com/github_username/escobar/issues
Project-URL: Repository, https://github.com/github_username/escobar.git
Author-email: Escobar <me@test.com>
License: BSD 3-Clause License
License-File: LICENSE
Classifier: Framework :: Jupyter
Classifier: Framework :: Jupyter :: JupyterLab
Classifier: Framework :: Jupyter :: JupyterLab :: 4
Classifier: Framework :: Jupyter :: JupyterLab :: Extensions
Classifier: Framework :: Jupyter :: JupyterLab :: Extensions :: Prebuilt
Classifier: License :: OSI Approved :: BSD License
Classifier: Programming Language :: Python
Classifier: Programming Language :: Python :: 3
Classifier: Programming Language :: Python :: 3.8
Classifier: Programming Language :: Python :: 3.9
Classifier: Programming Language :: Python :: 3.10
Classifier: Programming Language :: Python :: 3.11
Classifier: Programming Language :: Python :: 3.12
Requires-Python: >=3.8
Requires-Dist: aiohttp
Requires-Dist: google-auth-oauthlib>=0.5.0
Requires-Dist: google-auth>=2.0.0
Requires-Dist: jupyter-server>=2.0.0
Requires-Dist: websockets>=11.0
